byted_overpass_ecom_algo_fee_rate_pricing/__init__.py
byted_overpass_ecom_algo_fee_rate_pricing-0.0.1.dist-info/METADATA
byted_overpass_ecom_algo_fee_rate_pricing-0.0.1.dist-info/WHEEL
byted_overpass_ecom_algo_fee_rate_pricing-0.0.1.dist-info/top_level.txt
byted_overpass_ecom_algo_fee_rate_pricing-0.0.1.dist-info/RECORD
